pyvuejs/__init__.py
pyvuejs/_vue.py
pyvuejs/_assets/__init__.py
pyvuejs/_assets/axios.min.js
pyvuejs/_assets/axios.min.map
pyvuejs/_assets/favicon.ico
pyvuejs/_assets/pyvuejs.css
pyvuejs/_assets/pyvuejs.router.js
pyvuejs/_assets/vue.min.js
pyvuejs-2.0.5.post3.dist-info/LICENSE
pyvuejs-2.0.5.post3.dist-info/LICENSE.vbuild
pyvuejs-2.0.5.post3.dist-info/METADATA
pyvuejs-2.0.5.post3.dist-info/WHEEL
pyvuejs-2.0.5.post3.dist-info/entry_points.txt
pyvuejs-2.0.5.post3.dist-info/top_level.txt
pyvuejs-2.0.5.post3.dist-info/RECORD
