Metadata-Version: 2.1
Name: pyvuejs
Version: 2.0.5.post3
Summary: Pythonic Vue.js
Home-page: https://github.com/eseunghwan/pyvuejs
Author: eseunghwan
Author-email: shlee0920@naver.com
License: MIT license
Keywords: vue
Platform: UNKNOWN
Classifier: Development Status :: 2 - Pre-Alpha
Classifier: License :: OSI Approved :: MIT License
Classifier: Natural Language :: English
Classifier: Programming Language :: Python :: 3
Requires-Python: >=3.7
Requires-Dist: bottle
Requires-Dist: vbuild
Requires-Dist: pyscss
Requires-Dist: lesscpy
Requires-Dist: closure
